gui_decorator/__init__.py
gui_decorator/main.py
gui_decorator-0.0.2.dist-info/METADATA
gui_decorator-0.0.2.dist-info/WHEEL
gui_decorator-0.0.2.dist-info/top_level.txt
gui_decorator-0.0.2.dist-info/RECORD
