Metadata-Version: 2.4
Name: gui-decorator
Version: 0.0.2
Summary: Give me a GUI
Author-email: Long Tan <tanloong@foxmail.com>
Requires-Python: >=3.13
